simple_crawl/Thread_run.py
simple_crawl/Threads_run.py
simple_crawl/__init__.py
simple_crawl/asyn_run.py
simple_crawl/double.py
simple_crawl/ip_proxy.py
simple_crawl/multiproces.py
simple_crawl/request.py
simple_crawl/write_SQL.py
simple_crawl-0.0.9.dist-info/LICENSE
simple_crawl-0.0.9.dist-info/METADATA
simple_crawl-0.0.9.dist-info/WHEEL
simple_crawl-0.0.9.dist-info/top_level.txt
simple_crawl-0.0.9.dist-info/RECORD
