Metadata-Version: 2.1
Name: simple-crawl
Version: 0.0.9
Summary: Only need one line to crawl
Home-page: https://github.com/Amiee-well/crawl
Author: Lux
Author-email: 1223411083@qq.com
License: UNKNOWN
Project-URL: Blog, https://blog.csdn.net/qq_45414559/article/details/106005684
Platform: UNKNOWN
Classifier: Programming Language :: Python :: 3
Classifier: License :: OSI Approved :: MIT License
Classifier: Operating System :: OS Independent
Requires-Dist: requests
Requires-Dist: DecryptLogin
Requires-Dist: cleancc
Requires-Dist: lxml
Requires-Dist: beautifulsoup4
Requires-Dist: pymysql
Requires-Dist: aiohttp
Requires-Dist: asyncio
